models/__init__.py
models/pt_core_news_sm_addresses/config.cfg
models/pt_core_news_sm_addresses/entity_ruler/cfg
models/pt_core_news_sm_addresses/entity_ruler/patterns.jsonl
models/pt_core_news_sm_addresses/meta.json
models/pt_core_news_sm_addresses/tokenizer
models/pt_core_news_sm_addresses/vocab/key2row
models/pt_core_news_sm_addresses/vocab/lookups.bin
models/pt_core_news_sm_addresses/vocab/strings.json
models/pt_core_news_sm_addresses/vocab/vectors
tomba/__init__.py
tomba/generate_train_data.py
tomba/models.py
tomba/tomba.py
tomba-0.1.1a1.dist-info/LICENSE
tomba-0.1.1a1.dist-info/WHEEL
tomba-0.1.1a1.dist-info/METADATA
tomba-0.1.1a1.dist-info/RECORD
