Metadata-Version: 2.1
Name: tomba
Version: 0.1.1a1
Summary: Identifique localizações brasileiras em um texto 🏘
License: MIT
Author: Dados Abertos de Feira
Author-email: dadosabertosdefeira+gh@gmail.com
Requires-Python: >=3.8,<4.0
Classifier: License :: OSI Approved :: MIT License
Classifier: Programming Language :: Python :: 3
Classifier: Programming Language :: Python :: 3.8
Classifier: Programming Language :: Python :: 3.9
Requires-Dist: jupyter (>=1.0.0,<2.0.0)
Requires-Dist: pandas (>=1.2.1,<2.0.0)
Requires-Dist: setuptools (>=53.0.0,<54.0.0)
Requires-Dist: spacy (>=3.0.0)
Requires-Dist: wheel (>=0.36.2,<0.37.0)
